parrotizer/__init__.py
parrotizer/__version__.py
parrotizer-0.0.2.dist-info/METADATA
parrotizer-0.0.2.dist-info/RECORD
parrotizer-0.0.2.dist-info/WHEEL
parrotizer-0.0.2.dist-info/entry_points.txt
parrotizer-0.0.2.dist-info/top_level.txt
