Metadata-Version: 2.1
Name: parrotizer
Version: 0.0.2
Summary: Turn text into a slackmoji-parrotized text
Home-page: https://github.com/bradsbrown/parrotizer
Author: Brad Brown
Author-email: brad@bradsbrown.com
License: MIT
Platform: UNKNOWN
Classifier: Programming Language :: Python :: 3
Classifier: License :: OSI Approved :: MIT License
Classifier: Operating System :: OS Independent
Requires-Dist: pyperclip
